{
  "http://localhost:4000/": "https://storage.googleapis.com/lighthouse-infrastructure.appspot.com/reports/1745340818773-44449.report.html",
  "http://localhost:4000/about/": "https://storage.googleapis.com/lighthouse-infrastructure.appspot.com/reports/1745340819124-57693.report.html",
  "http://localhost:4000/blog/": "https://storage.googleapis.com/lighthouse-infrastructure.appspot.com/reports/1745340819401-56327.report.html",
  "http://localhost:4000/contact/": "https://storage.googleapis.com/lighthouse-infrastructure.appspot.com/reports/1745340819625-49993.report.html",
  "http://localhost:4000/projects/": "https://storage.googleapis.com/lighthouse-infrastructure.appspot.com/reports/1745340819893-88688.report.html"
}